bonchapi/__init__.py
bonchapi/bonchapi.py
bonchapi/parser.py
bonchapi/schemas.py
bonchapi/validator.py
bonchapi-0.0.7.dist-info/METADATA
bonchapi-0.0.7.dist-info/WHEEL
bonchapi-0.0.7.dist-info/licenses/LICENSE
bonchapi-0.0.7.dist-info/RECORD
