Metadata-Version: 2.4
Name: bonchapi
Version: 0.0.7
Summary: API client for lk.sut.ru
Project-URL: Documentation, https://github.com/KarimullinArthur/BonchAPI#readme
Project-URL: Issues, https://github.com/KarimullinArthur/BonchAPI/issues
Project-URL: Source, https://github.com/KarimullinArthur/BonchAPI
Author-email: Karimullin Arthur <KarimullinArthur@disroot.org>
License:                     GNU GENERAL PUBLIC LICENSE
License-File: LICENSE
Keywords: API,API-client,Bonch,SPbSUT,lk.sut.ru
Classifier: Development Status :: 4 - Beta
Classifier: Programming Language :: Python
Classifier: Programming Language :: Python :: 3.8
Classifier: Programming Language :: Python :: 3.9
Classifier: Programming Language :: Python :: 3.10
Classifier: Programming Language :: Python :: 3.11
Classifier: Programming Language :: Python :: 3.12
Classifier: Programming Language :: Python :: Implementation :: CPython
Classifier: Programming Language :: Python :: Implementation :: PyPy
Requires-Python: >=3.8
Requires-Dist: aiohttp
Requires-Dist: beautifulsoup4
Requires-Dist: lxml
